{
    "CAT": {
        "SLEEP": {
            "PATH": "../../assets/cat/sleep/sleep_",
            "FRAMES": 9,
            "DELAY": 500
        },
        "IDLE_FRONT": {
            "PATH": "../../assets/cat/idle_front/idle_",
            "FRAMES": 3,
            "DELAY": 800
        },
        "IDLE_BACK": {
            "PATH": "../../assets/cat/idle_back/idle_",
            "FRAMES": 3,
            "DELAY": 100
        },
        "RUN": {
            "PATH": "../../assets/cat/run/run_",
            "FRAMES": 3,
            "DELAY": 100
        },
        "WALK": {
            "PATH": "../../assets/cat/walk/walk_",
            "FRAMES": 3,
            "DELAY": 100
        }
    }
}